pwny/__init__.py
pwny/validation.py
django_pwny-0.2.17.dist-info/LICENSE
django_pwny-0.2.17.dist-info/METADATA
django_pwny-0.2.17.dist-info/WHEEL
django_pwny-0.2.17.dist-info/RECORD
