Metadata-Version: 2.1
Name: django-pwny
Version: 0.2.17
Summary: Have I Been Pwned? password validator
License: Apache-2.0
Author: PsypherPunk
Author-email: psypherpunk@gmail.com
Requires-Python: >=3.10,<4.0
Classifier: License :: OSI Approved :: Apache Software License
Classifier: Programming Language :: Python :: 3
Classifier: Programming Language :: Python :: 3.10
Classifier: Programming Language :: Python :: 3.11
Classifier: Programming Language :: Python :: 3.12
Requires-Dist: django (>=5.0.7,<6.0.0)
